nonebot_plugin_talk_with_poe_ai/__init__.py
nonebot_plugin_talk_with_poe_ai/async_poe_client/__init__.py
nonebot_plugin_talk_with_poe_ai/async_poe_client/client.py
nonebot_plugin_talk_with_poe_ai/async_poe_client/poe_graphql/AddHumanMessageMutation.graphql
nonebot_plugin_talk_with_poe_ai/async_poe_client/poe_graphql/AddMessageBreakMutation.graphql
nonebot_plugin_talk_with_poe_ai/async_poe_client/poe_graphql/AutoSubscriptionMutation.graphql
nonebot_plugin_talk_with_poe_ai/async_poe_client/poe_graphql/availableBotsListModalPaginationQuery.graphql
nonebot_plugin_talk_with_poe_ai/async_poe_client/poe_graphql/BioFragment.graphql
nonebot_plugin_talk_with_poe_ai/async_poe_client/poe_graphql/BotDeletionButton_poeBotDelete_Mutation.graphql
nonebot_plugin_talk_with_poe_ai/async_poe_client/poe_graphql/ChatAddedSubscription.graphql
nonebot_plugin_talk_with_poe_ai/async_poe_client/poe_graphql/ChatFragment.graphql
nonebot_plugin_talk_with_poe_ai/async_poe_client/poe_graphql/ChatListPaginationQuery.graphql
nonebot_plugin_talk_with_poe_ai/async_poe_client/poe_graphql/ChatPaginationQuery.graphql
nonebot_plugin_talk_with_poe_ai/async_poe_client/poe_graphql/ChatViewQuery.graphql
nonebot_plugin_talk_with_poe_ai/async_poe_client/poe_graphql/DeleteHumanMessagesMutation.graphql
nonebot_plugin_talk_with_poe_ai/async_poe_client/poe_graphql/DeleteMessageMutation.graphql
nonebot_plugin_talk_with_poe_ai/async_poe_client/poe_graphql/DeleteUserMessagesMutation.graphql
nonebot_plugin_talk_with_poe_ai/async_poe_client/poe_graphql/ExploreBotsListPaginationQuery.graphql
nonebot_plugin_talk_with_poe_ai/async_poe_client/poe_graphql/HandleFragment.graphql
nonebot_plugin_talk_with_poe_ai/async_poe_client/poe_graphql/LoginWithVerificationCodeMutation.graphql
nonebot_plugin_talk_with_poe_ai/async_poe_client/poe_graphql/MessageAddedSubscription.graphql
nonebot_plugin_talk_with_poe_ai/async_poe_client/poe_graphql/MessageDeletedSubscription.graphql
nonebot_plugin_talk_with_poe_ai-0.1.6.dist-info/METADATA
nonebot_plugin_talk_with_poe_ai-0.1.6.dist-info/WHEEL
nonebot_plugin_talk_with_poe_ai-0.1.6.dist-info/RECORD
