Metadata-Version: 2.1
Name: nonebot-plugin-talk-with-poe-ai
Version: 0.1.6
Summary: Nonebot2 基于poe cookie登录AI聊天插件
Home-page: https://github.com/nikissXI/nonebot_plugins/tree/main/nonebot_plugin_talk_with_poe_ai
License: MIT
Author: nikissXI
Author-email: 1299577815@qq.com
Requires-Python: >=3.8
Classifier: License :: OSI Approved :: MIT License
Classifier: Programming Language :: Python :: 3
Classifier: Programming Language :: Python :: 3.8
Classifier: Programming Language :: Python :: 3.9
Classifier: Programming Language :: Python :: 3.10
Classifier: Programming Language :: Python :: 3.11
Requires-Dist: Pillow (>=9.0.0)
Requires-Dist: aiohttp (>=3.8.4)
Requires-Dist: aiohttp_socks (>=0.8.0)
Requires-Dist: loguru (>=0.7.0)
Requires-Dist: nonebot-adapter-onebot (>=2.0.0)
Requires-Dist: nonebot2 (>=2.0.0rc1)
Project-URL: Documentation, https://github.com/nikissXI/nonebot_plugins/tree/main/nonebot_plugin_talk_with_poe_ai#README.md
Project-URL: Repository, https://github.com/nikissXI/nonebot_plugins/tree/main/nonebot_plugin_talk_with_poe_ai
